arithmetic.py
simple_arithmetic-0.0.1.dist-info/LICENSE
simple_arithmetic-0.0.1.dist-info/METADATA
simple_arithmetic-0.0.1.dist-info/WHEEL
simple_arithmetic-0.0.1.dist-info/top_level.txt
simple_arithmetic-0.0.1.dist-info/RECORD
